{
    "room_dim": [
        5,
        5,
        5
    ],
    "rt60": 0.5,
    "mic_amount": 4,
    "mic_start": [
        1,
        1,
        2.5
    ],
    "mic_dist": 0.1,
    "source_pos": [
        [
            2.5,
            2.5,
            0.0
        ],
        [
            2.5,
            2.5,
            0.033557
        ],
        [
            2.5,
            2.5,
            0.067114
        ],
        [
            2.5,
            2.5,
            0.100671
        ],
        [
            2.5,
            2.5,
            0.134228
        ],
        [
            2.5,
            2.5,
            0.167785
        ],
        [
            2.5,
            2.5,
            0.201342
        ],
        [
            2.5,
            2.5,
            0.234899
        ],
        [
            2.5,
            2.5,
            0.268456
        ],
        [
            2.5,
            2.5,
            0.302013
        ],
        [
            2.5,
            2.5,
            0.33557
        ],
        [
            2.5,
            2.5,
            0.369128
        ],
        [
            2.5,
            2.5,
            0.402685
        ],
        [
            2.5,
            2.5,
            0.436242
        ],
        [
            2.5,
            2.5,
            0.469799
        ],
        [
            2.5,
            2.5,
            0.503356
        ],
        [
            2.5,
            2.5,
            0.536913
        ],
        [
            2.5,
            2.5,
            0.57047
        ],
        [
            2.5,
            2.5,
            0.604027
        ],
        [
            2.5,
            2.5,
            0.637584
        ],
        [
            2.5,
            2.5,
            0.671141
        ],
        [
            2.5,
            2.5,
            0.704698
        ],
        [
            2.5,
            2.5,
            0.738255
        ],
        [
            2.5,
            2.5,
            0.771812
        ],
        [
            2.5,
            2.5,
            0.805369
        ],
        [
            2.5,
            2.5,
            0.838926
        ],
        [
            2.5,
            2.5,
            0.872483
        ],
        [
            2.5,
            2.5,
            0.90604
        ],
        [
            2.5,
            2.5,
            0.939597
        ],
        [
            2.5,
            2.5,
            0.973154
        ],
        [
            2.5,
            2.5,
            1.006711
        ],
        [
            2.5,
            2.5,
            1.040268
        ],
        [
            2.5,
            2.5,
            1.073826
        ],
        [
            2.5,
            2.5,
            1.107383
        ],
        [
            2.5,
            2.5,
            1.14094
        ],
        [
            2.5,
            2.5,
            1.174497
        ],
        [
            2.5,
            2.5,
            1.208054
        ],
        [
            2.5,
            2.5,
            1.241611
        ],
        [
            2.5,
            2.5,
            1.275168
        ],
        [
            2.5,
            2.5,
            1.308725
        ],
        [
            2.5,
            2.5,
            1.342282
        ],
        [
            2.5,
            2.5,
            1.375839
        ],
        [
            2.5,
            2.5,
            1.409396
        ],
        [
            2.5,
            2.5,
            1.442953
        ],
        [
            2.5,
            2.5,
            1.47651
        ],
        [
            2.5,
            2.5,
            1.510067
        ],
        [
            2.5,
            2.5,
            1.543624
        ],
        [
            2.5,
            2.5,
            1.577181
        ],
        [
            2.5,
            2.5,
            1.610738
        ],
        [
            2.5,
            2.5,
            1.644295
        ],
        [
            2.5,
            2.5,
            1.677852
        ],
        [
            2.5,
            2.5,
            1.711409
        ],
        [
            2.5,
            2.5,
            1.744966
        ],
        [
            2.5,
            2.5,
            1.778523
        ],
        [
            2.5,
            2.5,
            1.812081
        ],
        [
            2.5,
            2.5,
            1.845638
        ],
        [
            2.5,
            2.5,
            1.879195
        ],
        [
            2.5,
            2.5,
            1.912752
        ],
        [
            2.5,
            2.5,
            1.946309
        ],
        [
            2.5,
            2.5,
            1.979866
        ],
        [
            2.5,
            2.5,
            2.013423
        ],
        [
            2.5,
            2.5,
            2.04698
        ],
        [
            2.5,
            2.5,
            2.080537
        ],
        [
            2.5,
            2.5,
            2.114094
        ],
        [
            2.5,
            2.5,
            2.147651
        ],
        [
            2.5,
            2.5,
            2.181208
        ],
        [
            2.5,
            2.5,
            2.214765
        ],
        [
            2.5,
            2.5,
            2.248322
        ],
        [
            2.5,
            2.5,
            2.281879
        ],
        [
            2.5,
            2.5,
            2.315436
        ],
        [
            2.5,
            2.5,
            2.348993
        ],
        [
            2.5,
            2.5,
            2.38255
        ],
        [
            2.5,
            2.5,
            2.416107
        ],
        [
            2.5,
            2.5,
            2.449664
        ],
        [
            2.5,
            2.5,
            2.483221
        ],
        [
            2.5,
            2.5,
            2.516779
        ],
        [
            2.5,
            2.5,
            2.550336
        ],
        [
            2.5,
            2.5,
            2.583893
        ],
        [
            2.5,
            2.5,
            2.61745
        ],
        [
            2.5,
            2.5,
            2.651007
        ],
        [
            2.5,
            2.5,
            2.684564
        ],
        [
            2.5,
            2.5,
            2.718121
        ],
        [
            2.5,
            2.5,
            2.751678
        ],
        [
            2.5,
            2.5,
            2.785235
        ],
        [
            2.5,
            2.5,
            2.818792
        ],
        [
            2.5,
            2.5,
            2.852349
        ],
        [
            2.5,
            2.5,
            2.885906
        ],
        [
            2.5,
            2.5,
            2.919463
        ],
        [
            2.5,
            2.5,
            2.95302
        ],
        [
            2.5,
            2.5,
            2.986577
        ],
        [
            2.5,
            2.5,
            3.020134
        ],
        [
            2.5,
            2.5,
            3.053691
        ],
        [
            2.5,
            2.5,
            3.087248
        ],
        [
            2.5,
            2.5,
            3.120805
        ],
        [
            2.5,
            2.5,
            3.154362
        ],
        [
            2.5,
            2.5,
            3.187919
        ],
        [
            2.5,
            2.5,
            3.221477
        ],
        [
            2.5,
            2.5,
            3.255034
        ],
        [
            2.5,
            2.5,
            3.288591
        ],
        [
            2.5,
            2.5,
            3.322148
        ],
        [
            2.5,
            2.5,
            3.355705
        ],
        [
            2.5,
            2.5,
            3.389262
        ],
        [
            2.5,
            2.5,
            3.422819
        ],
        [
            2.5,
            2.5,
            3.456376
        ],
        [
            2.5,
            2.5,
            3.489933
        ],
        [
            2.5,
            2.5,
            3.52349
        ],
        [
            2.5,
            2.5,
            3.557047
        ],
        [
            2.5,
            2.5,
            3.590604
        ],
        [
            2.5,
            2.5,
            3.624161
        ],
        [
            2.5,
            2.5,
            3.657718
        ],
        [
            2.5,
            2.5,
            3.691275
        ],
        [
            2.5,
            2.5,
            3.724832
        ],
        [
            2.5,
            2.5,
            3.758389
        ],
        [
            2.5,
            2.5,
            3.791946
        ],
        [
            2.5,
            2.5,
            3.825503
        ],
        [
            2.5,
            2.5,
            3.85906
        ],
        [
            2.5,
            2.5,
            3.892617
        ],
        [
            2.5,
            2.5,
            3.926174
        ],
        [
            2.5,
            2.5,
            3.959732
        ],
        [
            2.5,
            2.5,
            3.993289
        ],
        [
            2.5,
            2.5,
            4.026846
        ],
        [
            2.5,
            2.5,
            4.060403
        ],
        [
            2.5,
            2.5,
            4.09396
        ],
        [
            2.5,
            2.5,
            4.127517
        ],
        [
            2.5,
            2.5,
            4.161074
        ],
        [
            2.5,
            2.5,
            4.194631
        ],
        [
            2.5,
            2.5,
            4.228188
        ],
        [
            2.5,
            2.5,
            4.261745
        ],
        [
            2.5,
            2.5,
            4.295302
        ],
        [
            2.5,
            2.5,
            4.328859
        ],
        [
            2.5,
            2.5,
            4.362416
        ],
        [
            2.5,
            2.5,
            4.395973
        ],
        [
            2.5,
            2.5,
            4.42953
        ],
        [
            2.5,
            2.5,
            4.463087
        ],
        [
            2.5,
            2.5,
            4.496644
        ],
        [
            2.5,
            2.5,
            4.530201
        ],
        [
            2.5,
            2.5,
            4.563758
        ],
        [
            2.5,
            2.5,
            4.597315
        ],
        [
            2.5,
            2.5,
            4.630872
        ],
        [
            2.5,
            2.5,
            4.66443
        ],
        [
            2.5,
            2.5,
            4.697987
        ],
        [
            2.5,
            2.5,
            4.731544
        ],
        [
            2.5,
            2.5,
            4.765101
        ],
        [
            2.5,
            2.5,
            4.798658
        ],
        [
            2.5,
            2.5,
            4.832215
        ],
        [
            2.5,
            2.5,
            4.865772
        ],
        [
            2.5,
            2.5,
            4.899329
        ],
        [
            2.5,
            2.5,
            4.932886
        ],
        [
            2.5,
            2.5,
            4.966443
        ],
        [
            2.5,
            2.5,
            5.0
        ]
    ],
    "fs": 48000,
    "snr": 0
}